test_lib/__init__.py
with_/__init__.py
with_/cats/__init__.py
luna_has_unknown-1.dist-info/METADATA
luna_has_unknown-1.dist-info/WHEEL
luna_has_unknown-1.dist-info/top_level.txt
luna_has_unknown-1.dist-info/RECORD
