Metadata-Version: 2.1
Name: luna-has-unknown
Version: 1
Summary: _
Home-page: UNKNOWN
Author: gamergirl31
License: MIT
Platform: UNKNOWN
Classifier: Programming Language :: Python :: 3
Classifier: License :: OSI Approved :: MIT License
Requires-Python: >=3.6
